{"name":"Nigeria","code":"NG","regions":[{"name":"Abia State","code":"45","cities":[{"name":"Aba","latitude":"5.1066","longitude":"7.3667"},{"name":"Amaigbo","latitude":"5.7892","longitude":"7.8383"},{"name":"Umuahia","latitude":"5.5263","longitude":"7.4896"}]},{"name":"Adamawa","code":"35","cities":[{"name":"Nassarawa","latitude":"8.8333","longitude":"12.3333"},{"name":"Yola","latitude":"9.2","longitude":"12.4833"}]},{"name":"Akwa Ibom State","code":"21","cities":[{"name":"Uyo","latitude":"5.0345","longitude":"7.928"}]},{"name":"Anambra","code":"25","cities":[{"name":"Awka","latitude":"6.2132","longitude":"7.067"},{"name":"Enugu-Ukwu","latitude":"6.1785","longitude":"7.0116"},{"name":"Onitsha","latitude":"6.1388","longitude":"6.788"}]},{"name":"Bauchi","code":"46","cities":[{"name":"Bauchi","latitude":"10.3131","longitude":"9.8402"}]},{"name":"Bayelsa State","code":"52","cities":[{"name":"Yenagoa","latitude":"4.925","longitude":"6.2605"}]},{"name":"Benue State","code":"26","cities":[{"name":"Makurdi","latitude":"7.7411","longitude":"8.5121"}]},{"name":"Cross River State","code":"22","cities":[{"name":"Calabar","latitude":"4.9517","longitude":"8.322"},{"name":"Obudu","latitude":"6.6677","longitude":"9.1726"}]},{"name":"Delta","code":"36","cities":[{"name":"Abraka","latitude":"5.7902","longitude":"6.1047"},{"name":"Asaba","latitude":"6.2006","longitude":"6.7338"},{"name":"Burutu","latitude":"5.3567","longitude":"5.5053"},{"name":"Oleh","latitude":"5.4619","longitude":"6.2062"},{"name":"Warri","latitude":"5.5167","longitude":"5.75"}]},{"name":"Ebonyi State","code":"53","cities":[{"name":"Abakaliki","latitude":"6.3126","longitude":"8.1162"}]},{"name":"Edo","code":"37","cities":[{"name":"Benin City","latitude":"6.3332","longitude":"5.6238"},{"name":"Ogba","latitude":"6.0591","longitude":"6.1178"}]},{"name":"Ekiti State","code":"54","cities":[{"name":"Aboro","latitude":"7.7575","longitude":"5.0039"},{"name":"Ado-Ekiti","latitude":"7.629","longitude":"5.221"}]},{"name":"Enugu State","code":"47","cities":[{"name":"Amagu","latitude":"5.9541","longitude":"7.6923"},{"name":"Enugu","latitude":"6.4402","longitude":"7.4943"},{"name":"Nsukka","latitude":"6.8561","longitude":"7.3927"}]},{"name":"FCT","code":"11","cities":[{"name":"Abuja","latitude":"9.0833","longitude":"7.5333"},{"name":"Akori","latitude":"8.4667","longitude":"6.8333"},{"name":"Gwarinpa","latitude":"9.101","longitude":"7.4126"},{"name":"Kurudu","latitude":"8.9314","longitude":"7.55"},{"name":"Maitama","latitude":"9.101","longitude":"7.4919"},{"name":"Wuse","latitude":"9.0676","longitude":"7.4694"}]},{"name":"Gombe State","code":"55","cities":[{"name":"Akko","latitude":"10.2908","longitude":"10.9754"},{"name":"Pindiga","latitude":"9.9833","longitude":"10.9333"}]},{"name":"Imo State","code":"28","cities":[{"name":"Ibeku","latitude":"5.4658","longitude":"7.2626"},{"name":"Owerri","latitude":"5.4833","longitude":"7.0304"}]},{"name":"Jigawa State","code":"39","cities":[{"name":"Dutse","latitude":"11.758","longitude":"9.341"},{"name":"Hadejia","latitude":"12.4498","longitude":"10.0444"}]},{"name":"Kaduna State","code":"23","cities":[{"name":"Kaduna","latitude":"10.5222","longitude":"7.4383"},{"name":"Kakuri","latitude":"10.4547","longitude":"7.4129"},{"name":"Zaria","latitude":"11.1132","longitude":"7.7252"}]},{"name":"Kano State","code":"29","cities":[{"name":"Kano","latitude":"11.9944","longitude":"8.5138"}]},{"name":"Katsina State","code":"24","cities":[{"name":"Funtua","latitude":"11.5208","longitude":"7.3074"},{"name":"Katsina","latitude":"12.996","longitude":"7.6049"}]},{"name":"Kebbi","code":"40","cities":[{"name":"Argungu","latitude":"12.7433","longitude":"4.5269"},{"name":"Birnin Kebbi","latitude":"12.4523","longitude":"4.2002"},{"name":"Kamba","latitude":"11.8456","longitude":"3.6604"},{"name":"Zazagawa","latitude":"12.7014","longitude":"4.3714"}]},{"name":"Kogi State","code":"41","cities":[{"name":"Anambra","latitude":"7.2667","longitude":"7.4"},{"name":"Lokoja","latitude":"7.8016","longitude":"6.7505"}]},{"name":"Kwara State","code":"30","cities":[{"name":"Ilorin","latitude":"8.5","longitude":"4.55"}]},{"name":"Lagos","code":"05","cities":[{"name":"Ado","latitude":"6.4964","longitude":"3.5804"},{"name":"Agege","latitude":"6.614","longitude":"3.3191"},{"name":"Ajah","latitude":"6.4696","longitude":"3.5629"},{"name":"Alimosho","latitude":"6.6108","longitude":"3.2961"},{"name":"Apapa","latitude":"6.4374","longitude":"3.4166"},{"name":"Badagry","latitude":"6.4167","longitude":"2.8833"},{"name":"Badore","latitude":"6.4333","longitude":"3.85"},{"name":"Dopemu","latitude":"6.6139","longitude":"3.3192"},{"name":"Egba","latitude":"6.6395","longitude":"3.2899"},{"name":"Gbagada","latitude":"6.5507","longitude":"3.392"},{"name":"Iba","latitude":"6.4873","longitude":"3.9069"},{"name":"Igando","latitude":"6.4365","longitude":"3.816"},{"name":"Ijegun","latitude":"6.5164","longitude":"3.2549"},{"name":"Ikeja","latitude":"6.5942","longitude":"3.3375"},{"name":"Ikorodu","latitude":"6.6155","longitude":"3.5087"},{"name":"Ikotun","latitude":"6.4497","longitude":"3.0874"},{"name":"Ikoyi","latitude":"6.4561","longitude":"3.4422"},{"name":"Ipaja","latitude":"6.6078","longitude":"3.2526"},{"name":"Isaga-Tedo","latitude":"6.5267","longitude":"3.3258"},{"name":"Isolo","latitude":"6.5331","longitude":"3.3171"},{"name":"Ketu","latitude":"6.6309","longitude":"3.88"},{"name":"Lagos","latitude":"6.4474","longitude":"3.3903"},{"name":"Lekki","latitude":"6.4095","longitude":"4.0915"},{"name":"Magodo II","latitude":"6.6278","longitude":"3.3906"},{"name":"Maryland","latitude":"6.5699","longitude":"3.37"},{"name":"Meiran","latitude":"6.6527","longitude":"3.2648"},{"name":"Mushin","latitude":"6.5263","longitude":"3.3571"},{"name":"Ogudu","latitude":"6.5673","longitude":"3.3947"},{"name":"Ojo","latitude":"6.4538","longitude":"3.2058"},{"name":"Ojodu","latitude":"6.6443","longitude":"3.3641"},{"name":"Ojota","latitude":"6.5921","longitude":"3.3791"},{"name":"Oregun","latitude":"6.4845","longitude":"3.6313"},{"name":"Oshodi","latitude":"6.5582","longitude":"3.3466"},{"name":"Oworonsoki","latitude":"6.545","longitude":"3.411"},{"name":"Shogunle","latitude":"6.5767","longitude":"3.3386"},{"name":"Somolu","latitude":"6.5464","longitude":"3.3721"},{"name":"Surulere","latitude":"6.5015","longitude":"3.3581"},{"name":"Yaba","latitude":"6.4981","longitude":"3.3844"}]},{"name":"Nasarawa State","code":"56","cities":[{"name":"Jikoyi","latitude":"8.9678","longitude":"7.5687"}]},{"name":"Niger State","code":"31","cities":[{"name":"Minna","latitude":"9.6139","longitude":"6.5569"},{"name":"Suleja","latitude":"9.1766","longitude":"7.1751"}]},{"name":"Ogun State","code":"16","cities":[{"name":"Abalabi","latitude":"6.8685","longitude":"3.1305"},{"name":"Abeokuta","latitude":"7.1472","longitude":"3.3505"},{"name":"Agbara","latitude":"6.5022","longitude":"3.1051"},{"name":"Ibadan","latitude":"6.5323","longitude":"2.7689"},{"name":"Ifo","latitude":"6.8144","longitude":"3.1958"},{"name":"Igbokofi","latitude":"7.1333","longitude":"2.7667"},{"name":"Ijebu Ode","latitude":"6.8161","longitude":"3.9159"},{"name":"Ilishan","latitude":"6.8879","longitude":"3.7161"},{"name":"Kogi","latitude":"7.1333","longitude":"3.5667"},{"name":"Mowe","latitude":"6.8107","longitude":"3.4366"},{"name":"Ota","latitude":"6.6833","longitude":"3.2367"},{"name":"Sagamu","latitude":"6.8432","longitude":"3.6478"}]},{"name":"Ondo State","code":"48","cities":[{"name":"Akure","latitude":"7.2526","longitude":"5.1931"}]},{"name":"Osun State","code":"42","cities":[{"name":"Ile-Ife","latitude":"7.4592","longitude":"4.5685"},{"name":"Ilesa","latitude":"7.6122","longitude":"4.7351"},{"name":"Osogbo","latitude":"7.7667","longitude":"4.5667"}]},{"name":"Oyo State","code":"32","cities":[{"name":"Abidogun","latitude":"7.3333","longitude":"3.3333"},{"name":"Ibadan","latitude":"7.3886","longitude":"3.8961"},{"name":"Oyo","latitude":"7.85","longitude":"3.9333"},{"name":"Sango","latitude":"7.4275","longitude":"3.8803"}]},{"name":"Plateau State","code":"49","cities":[{"name":"Jos","latitude":"9.9167","longitude":"8.9"},{"name":"Langtang","latitude":"9.1414","longitude":"9.7821"}]},{"name":"Rivers State","code":"50","cities":[{"name":"Bonny","latitude":"4.4522","longitude":"7.1681"},{"name":"Egbeda","latitude":"5.2341","longitude":"6.7519"},{"name":"Port Harcourt","latitude":"4.7774","longitude":"7.0134"}]},{"name":"Sokoto State","code":"51","cities":[{"name":"Kebbe","latitude":"12.1348","longitude":"4.7341"}]},{"name":"Taraba State","code":"43","cities":[{"name":"Gembu","latitude":"6.7","longitude":"11.2667"},{"name":"Jalingo","latitude":"8.8786","longitude":"11.3632"},{"name":"Wukari","latitude":"7.8488","longitude":"9.7872"}]},{"name":"Yobe State","code":"44","cities":[{"name":"Damaturu","latitude":"11.747","longitude":"11.9608"}]},{"name":"Zamfara State","code":"57","cities":[{"name":"Gusau","latitude":"12.1628","longitude":"6.6613"},{"name":"Tsafe","latitude":"11.9542","longitude":"6.9165"}]}]}