{"name":"Eswatini","code":"SZ","regions":[{"name":"Hhohho","code":"01","cities":[{"name":"Lobamba","latitude":"-26.4666","longitude":"31.1936"},{"name":"Mbabane","latitude":"-26.3167","longitude":"31.1333"}]},{"name":"Lubombo District","code":"02","cities":[{"name":"Big Bend","latitude":"-26.8198","longitude":"31.9357"},{"name":"Ezulwini","latitude":"-26.4","longitude":"31.1667"},{"name":"Simunye","latitude":"-26.2078","longitude":"31.9162"}]},{"name":"Manzini","code":"03","cities":[{"name":"Malkerns","latitude":"-26.5667","longitude":"31.1833"},{"name":"Manzini","latitude":"-26.4814","longitude":"31.3651"},{"name":"Matsapha","latitude":"-26.5167","longitude":"31.3167"}]},{"name":"Shiselweni District","code":"04","cities":[{"name":"Kubuta","latitude":"-26.8833","longitude":"31.4833"},{"name":"Nhlangano","latitude":"-27.1172","longitude":"31.2013"}]}]}